{
    "Acadgild": {
        "accreditation": "None", 
        "average_salary": "N/A", 
        "class_ratio": null, 
        "courses": {
            "Advance J2Ee": {
                "Cost": 600, 
                "Hours/Week": null, 
                "Location": [
                    "Online"
                ], 
                "Minimum Skill": null, 
                "Onsite": "Online", 
                "Part Or Full": "Part Time", 
                "Subjects": [
                    "Java"
                ], 
                "Title": "Advance J2ee"
            }, 
            "Android Development": {
                "Cost": 600, 
                "Hours/Week": 3, 
                "Location": [
                    "Online"
                ], 
                "Minimum Skill": null, 
                "Onsite": "Online", 
                "Part Or Full": "Part Time", 
                "Subjects": [
                    "Git", 
                    "Android"
                ], 
                "Title": "Android Development"
            }, 
            "Android Programming For Children": {
                "Cost": 499, 
                "Hours/Week": null, 
                "Location": [
                    "Online"
                ], 
                "Minimum Skill": null, 
                "Onsite": "Online", 
                "Part Or Full": "Part Time", 
                "Subjects": [
                    "Java", 
                    "Android"
                ], 
                "Title": "Android Programming for Children"
            }, 
            "Apache Spark": {
                "Cost": 600, 
                "Hours/Week": null, 
                "Location": [
                    "Online"
                ], 
                "Minimum Skill": null, 
                "Onsite": "Online", 
                "Part Or Full": "Part Time", 
                "Subjects": [
                    "Spark"
                ], 
                "Title": "Apache Spark"
            }, 
            "Arduino For Children": {
                "Cost": 499, 
                "Hours/Week": 6, 
                "Location": [
                    "Online"
                ], 
                "Minimum Skill": null, 
                "Onsite": "Online", 
                "Part Or Full": "Part Time", 
                "Subjects": [], 
                "Title": "Arduino for Children"
            }, 
            "Big Data And Hadoop Administration": {
                "Cost": 600, 
                "Hours/Week": 6, 
                "Location": [
                    "Online"
                ], 
                "Minimum Skill": null, 
                "Onsite": "Online", 
                "Part Or Full": "Full Time", 
                "Subjects": [
                    "Data Science", 
                    "Hadoop"
                ], 
                "Title": "Big Data and Hadoop Administration"
            }, 
            "Big Data And Hadoop Development": {
                "Cost": 600, 
                "Hours/Week": 3, 
                "Location": [
                    "Online"
                ], 
                "Minimum Skill": null, 
                "Onsite": "Online", 
                "Part Or Full": "Part Time", 
                "Subjects": [
                    "Data Science", 
                    "Hadoop"
                ], 
                "Title": "Big Data and Hadoop Development"
            }, 
            "Business Analytics With R": {
                "Cost": 600, 
                "Hours/Week": null, 
                "Location": [
                    "Online"
                ], 
                "Minimum Skill": null, 
                "Onsite": "Online", 
                "Part Or Full": "Part Time", 
                "Subjects": [
                    "R"
                ], 
                "Title": "Business Analytics with R"
            }, 
            "Cloud Bundle": {
                "Cost": 1199, 
                "Hours/Week": 3, 
                "Location": [
                    "Online"
                ], 
                "Minimum Skill": null, 
                "Onsite": "Online", 
                "Part Or Full": "Part Time", 
                "Subjects": [
                    "Hadoop"
                ], 
                "Title": "Cloud Bundle"
            }, 
            "Cloud Computing ": {
                "Cost": 600, 
                "Hours/Week": 3, 
                "Location": [
                    "Online"
                ], 
                "Minimum Skill": null, 
                "Onsite": "Online", 
                "Part Or Full": "Full Time", 
                "Subjects": [], 
                "Title": "Cloud Computing "
            }, 
            "Core Java": {
                "Cost": 600, 
                "Hours/Week": null, 
                "Location": [
                    "Online"
                ], 
                "Minimum Skill": null, 
                "Onsite": "Online", 
                "Part Or Full": "Part Time", 
                "Subjects": [
                    "Java"
                ], 
                "Title": "Core Java"
            }, 
            "Data Science Bundle": {
                "Cost": 1199, 
                "Hours/Week": null, 
                "Location": [
                    "Online"
                ], 
                "Minimum Skill": null, 
                "Onsite": "Online", 
                "Part Or Full": "Part Time", 
                "Subjects": [
                    "Data Science", 
                    "R", 
                    "Hadoop"
                ], 
                "Title": "Data Science Bundle"
            }, 
            "Digital Marketing": {
                "Cost": 600, 
                "Hours/Week": 3, 
                "Location": [
                    "Online"
                ], 
                "Minimum Skill": null, 
                "Onsite": "Online", 
                "Part Or Full": "Full Time", 
                "Subjects": [
                    "Digital Marketing"
                ], 
                "Title": "Digital marketing"
            }, 
            "Front End Web Development": {
                "Cost": 600, 
                "Hours/Week": 3, 
                "Location": [
                    "Online"
                ], 
                "Minimum Skill": null, 
                "Onsite": "Online", 
                "Part Or Full": "Part Time", 
                "Subjects": [
                    "JavaScript", 
                    "HTML", 
                    "CSS"
                ], 
                "Title": "Front End Web Development"
            }, 
            "Frontend Bundle": {
                "Cost": 1199, 
                "Hours/Week": 4, 
                "Location": [
                    "Online"
                ], 
                "Minimum Skill": null, 
                "Onsite": "Online", 
                "Part Or Full": "Full Time", 
                "Subjects": [
                    "Front End", 
                    "HTML", 
                    "CSS", 
                    "Node.js"
                ], 
                "Title": "Frontend Bundle"
            }, 
            "Frontend Web Development Fundamentals ": {
                "Cost": 600, 
                "Hours/Week": null, 
                "Location": [
                    "Online"
                ], 
                "Minimum Skill": null, 
                "Onsite": "Online", 
                "Part Or Full": "Full Time", 
                "Subjects": [
                    "JavaScript", 
                    "HTML", 
                    "CSS"
                ], 
                "Title": "Frontend Web Development Fundamentals "
            }, 
            "Full Stack Web Development": {
                "Cost": 600, 
                "Hours/Week": 3, 
                "Location": [
                    "Online"
                ], 
                "Minimum Skill": null, 
                "Onsite": "Online", 
                "Part Or Full": "Part Time", 
                "Subjects": [
                    "JavaScript", 
                    "HTML", 
                    "Git", 
                    "Rails", 
                    "Ruby", 
                    "CSS"
                ], 
                "Title": "Full Stack Web Development"
            }, 
            "Machine Learning With R": {
                "Cost": 600, 
                "Hours/Week": 3, 
                "Location": [
                    "Online"
                ], 
                "Minimum Skill": null, 
                "Onsite": "Online", 
                "Part Or Full": "Full Time", 
                "Subjects": [
                    "R"
                ], 
                "Title": "Machine Learning with R"
            }, 
            "Mobile Bundle": {
                "Cost": 1199, 
                "Hours/Week": 3, 
                "Location": [
                    "Online"
                ], 
                "Minimum Skill": null, 
                "Onsite": "Online", 
                "Part Or Full": "Part Time", 
                "Subjects": [
                    "Java", 
                    "Android", 
                    "Node.js"
                ], 
                "Title": "Mobile Bundle"
            }, 
            "Mongodb": {
                "Cost": 600, 
                "Hours/Week": 6, 
                "Location": [
                    "Online"
                ], 
                "Minimum Skill": null, 
                "Onsite": "Online", 
                "Part Or Full": "Full Time", 
                "Subjects": [
                    "MongoDB"
                ], 
                "Title": "MongoDB"
            }, 
            "Node.Js": {
                "Cost": 600, 
                "Hours/Week": 3, 
                "Location": [
                    "Online"
                ], 
                "Minimum Skill": null, 
                "Onsite": "Online", 
                "Part Or Full": "Part Time", 
                "Subjects": [
                    "HTML"
                ], 
                "Title": "Node.js"
            }, 
            "Python Programming For Children": {
                "Cost": 499, 
                "Hours/Week": 3, 
                "Location": [
                    "Online"
                ], 
                "Minimum Skill": null, 
                "Onsite": "Online", 
                "Part Or Full": "Part Time", 
                "Subjects": [
                    "Python"
                ], 
                "Title": "Python Programming for Children"
            }, 
            "Raspberry Pi For Childern": {
                "Cost": 499, 
                "Hours/Week": null, 
                "Location": [
                    "Online"
                ], 
                "Minimum Skill": null, 
                "Onsite": "Online", 
                "Part Or Full": "Part Time", 
                "Subjects": [
                    "Python"
                ], 
                "Title": "Raspberry Pi for Childern"
            }, 
            "Robotics For Children": {
                "Cost": 499, 
                "Hours/Week": 3, 
                "Location": [
                    "Online"
                ], 
                "Minimum Skill": null, 
                "Onsite": "Online", 
                "Part Or Full": "Part Time", 
                "Subjects": [], 
                "Title": "Robotics for Children"
            }, 
            "Unity 2D For Children": {
                "Cost": 499, 
                "Hours/Week": null, 
                "Location": [
                    "Online"
                ], 
                "Minimum Skill": null, 
                "Onsite": "Online", 
                "Part Or Full": "Part Time", 
                "Subjects": [
                    "Game Development"
                ], 
                "Title": "Unity 2D for Children"
            }
        }, 
        "cr_num_reviews": 32, 
        "cr_rating": 3.8, 
        "cr_technologies": [
            "Git", 
            "Android", 
            "JavaScript", 
            "HTML", 
            "CSS", 
            "Ruby on Rails", 
            "Ruby", 
            "Data Science", 
            "Hadoop", 
            "Java", 
            "Node.js", 
            "Python", 
            "Digital Marketing", 
            "R", 
            "Front End", 
            "MongoDB", 
            "Game Development", 
            "Spark"
        ], 
        "email": "enquiry@acadgild.com", 
        "facebook": "https://www.facebook.com/acadgild", 
        "general_cost": "$", 
        "hiring_rate": "No data", 
        "housing": "No", 
        "job_assistance": "Yes", 
        "job_guarantee": "No", 
        "last_updated": "2016-09-09", 
        "locations": [
            "Online", 
            "Bangalore"
        ], 
        "name": "Acadgild", 
        "num_alumni": "N/A", 
        "num_courses": 25, 
        "num_locations": 2, 
        "su_num_reviews": null, 
        "su_rating": null, 
        "su_technologies": null, 
        "subjects": "Android", 
        "technologies": [
            "Git", 
            "Android", 
            "JavaScript", 
            "HTML", 
            "CSS", 
            "Ruby on Rails", 
            "Ruby", 
            "Data Science", 
            "Hadoop", 
            "Java", 
            "Node.js", 
            "Python", 
            "Digital Marketing", 
            "R", 
            "Front End", 
            "MongoDB", 
            "Game Development", 
            "Spark"
        ], 
        "top_source": [
            "CourseReport"
        ], 
        "tracking_groups": [
            "Current Market", 
            "Cleveland"
        ], 
        "tracks": [
            "Other", 
            "Mobile Development", 
            "Front-End Web Development", 
            "Data Science", 
            "Digital Marketing", 
            "Full-Stack Web Development"
        ], 
        "twitter": {
            "followers": 850, 
            "handle": "@acadgild", 
            "tweets": 2265
        }, 
        "visas": "No", 
        "website": "http://acadgild.com/"
    }, 
    "Boole Institute": {
        "accreditation": "None", 
        "courses": {
            "Full Stack Web Development": {
                "Cost": null, 
                "Hours/Week": null, 
                "Location": [
                    "Cleveland"
                ], 
                "Minimum Skill": null, 
                "Onsite": null, 
                "Part Or Full": null, 
                "Subjects": [
                    "Front End", 
                    "JavaScript", 
                    "HTML", 
                    "Git", 
                    "jQuery", 
                    "CSS", 
                    "Express.js", 
                    "Node.js"
                ], 
                "Title": "Full Stack Web Development"
            }
        }, 
        "cr_num_reviews": 1, 
        "cr_rating": 5.0, 
        "cr_technologies": [
            "Front End", 
            "JavaScript", 
            "HTML", 
            "Git", 
            "jQuery", 
            "CSS", 
            "Express.js", 
            "Node.js"
        ], 
        "email": "contact@boole.co", 
        "facebook": "https://www.facebook.com/Boole-Institute-190552871301815/", 
        "housing": null, 
        "job_assistance": "Yes", 
        "job_guarantee": "No", 
        "last_updated": "2016-09-09", 
        "locations": [
            "Cleveland"
        ], 
        "name": "Boole Institute", 
        "num_courses": 1, 
        "num_locations": 1, 
        "technologies": [
            "Front End", 
            "JavaScript", 
            "HTML", 
            "Git", 
            "jQuery", 
            "CSS", 
            "Express.js", 
            "Node.js"
        ], 
        "top_source": [
            "CourseReport"
        ], 
        "tracking_groups": [
            "Current Market", 
            "Cleveland"
        ], 
        "tracks": "Full-Stack Web Development", 
        "twitter": "N/A", 
        "visas": "No", 
        "website": "http://www.boole.co/"
    }, 
    "Girl Develop It": {
        "average_salary": "N/A", 
        "class_ratio": null, 
        "courses": {}, 
        "general_cost": "$$$", 
        "hiring_rate": "No data", 
        "last_updated": "2016-09-09", 
        "locations": [
            "Boston", 
            "Los Angeles", 
            "San Francisco", 
            "San Diego", 
            "San Jose", 
            "Boulder", 
            "Denver", 
            "Fort Collins", 
            "Wilmington", 
            "Washington DC", 
            "Miami", 
            "Tampa", 
            "Atlanta", 
            "Boise", 
            "Chicago", 
            "Phoenix", 
            "West Palm Beach", 
            "Indianapolis", 
            "Louisville", 
            "Baltimore", 
            "Oakland", 
            "Ann Arbor", 
            "Detroit", 
            "Minneapolis", 
            "Kansas City", 
            "St. Louis", 
            "Camden", 
            "Albuquerque", 
            "Rochester", 
            "Buffalo", 
            "New York City", 
            "Charlotte", 
            "Raleigh", 
            "Cincinnati", 
            "Columbus", 
            "Providence", 
            "Dayton", 
            "Ottawa", 
            "Portland", 
            "Salt Lake City", 
            "Provo", 
            "Austin", 
            "Dallas", 
            "Houston", 
            "Philadelphia", 
            "Pittsburgh", 
            "Lehigh Valley", 
            "Milwaukee", 
            "Seattle", 
            "Burlington", 
            "Central Virginia"
        ], 
        "name": "Girl Develop It", 
        "num_alumni": "N/A", 
        "num_locations": 51, 
        "su_num_reviews": null, 
        "su_rating": null, 
        "su_technologies": null, 
        "subjects": "HTML/CSS, JavaScript, GIT/Github, web concepts, PHP/MySQL, Angular.JS., Web Accessibility", 
        "technologies": [], 
        "top_source": [
            "SwitchUp"
        ], 
        "tracking_groups": [
            "Potential Market", 
            "Detroit", 
            "Buffalo", 
            "Cincinnati", 
            "Current Market", 
            "Columbus", 
            "Pittsburgh"
        ], 
        "website": "https://www.girldevelopit.com/"
    }, 
    "Software Guild": {
        "accreditation": "Registered and compliant with the Ohio State Board of Career Colleges and Schools. Registration number is #13-11-2036T. Kentucky Commission on Proprietary Education, Resident School License No. R-0470", 
        "average_salary": 55000, 
        "class_ratio": "1 to 12", 
        "courses": {
            ".Net Web Developer Bootcamp": {
                "Class Size": 16, 
                "Cost": 10000, 
                "Hours/Week": 60, 
                "Length": "12 weeks", 
                "Location": [
                    "Akron"
                ], 
                "Start Date": "Rolling Dates", 
                "Subjects": [
                    "AngularJS", 
                    "CSS", 
                    "Data Structures", 
                    "HTML", 
                    "Javascript", 
                    ".NET", 
                    "SQL"
                ], 
                "Title": ".NET Web Developer Bootcamp"
            }, 
            ".Net/C#": {
                "Cost": null, 
                "Hours/Week": null, 
                "Location": [
                    "Online"
                ], 
                "Minimum Skill": null, 
                "Onsite": null, 
                "Part Or Full": null, 
                "Subjects": [
                    "AngularJS", 
                    "Front End", 
                    "JavaScript", 
                    ".NET", 
                    "HTML", 
                    "Git", 
                    "C#", 
                    "ASP.NET", 
                    "SQL", 
                    "jQuery", 
                    "CSS"
                ], 
                "Title": ".NET/C#"
            }, 
            "Java": {
                "Cost": null, 
                "Hours/Week": null, 
                "Location": [
                    "Online"
                ], 
                "Minimum Skill": null, 
                "Onsite": null, 
                "Part Or Full": null, 
                "Subjects": [
                    "MySQL", 
                    "AngularJS", 
                    "JavaScript", 
                    "HTML", 
                    "Git", 
                    "Java", 
                    "jQuery", 
                    "CSS"
                ], 
                "Title": "Java"
            }, 
            "Java Web Developer Bootcamp": {
                "Class Size": 16, 
                "Hours/Week": 60, 
                "Length": "12 weeks", 
                "Start Date": "Rolling Dates", 
                "Subjects": [
                    "CSS", 
                    "Data Structures", 
                    "HTML", 
                    "Java", 
                    "Javascript", 
                    "jQuery", 
                    "MySQL"
                ], 
                "Title": "Java Web Developer Bootcamp"
            }
        }, 
        "cr_num_reviews": 45, 
        "cr_rating": 4.8, 
        "cr_technologies": [
            "AngularJS", 
            "Front End", 
            "JavaScript", 
            ".NET", 
            "HTML", 
            "Git", 
            "C#", 
            "ASP.NET", 
            "SQL", 
            "jQuery", 
            "CSS", 
            "MySQL", 
            "Java"
        ], 
        "email": "info@thesoftwareguild.com", 
        "facebook": "https://www.facebook.com/thesoftwareguild", 
        "general_cost": "$$", 
        "hiring_rate": 95.0, 
        "housing": "The Software Guild offers short-term subleases to apartments in all three locations.", 
        "job_assistance": "Yes", 
        "job_guarantee": "No", 
        "last_updated": "2016-09-09", 
        "locations": [
            "Akron", 
            "Minneapolis", 
            "Louisville", 
            "Online"
        ], 
        "name": "Software Guild", 
        "num_alumni": "N/A", 
        "num_courses": 2, 
        "num_locations": 4, 
        "su_num_reviews": 24, 
        "su_rating": 4.8, 
        "su_technologies": [
            "AngularJS", 
            "CSS", 
            "Data Structures", 
            "HTML", 
            "JavaScript", 
            ".NET", 
            "SQL", 
            "Java", 
            "jQuery", 
            "MySQL"
        ], 
        "subjects": "Full Stack Web Development - Java or .NET, SQL Server / MySQL, HTML/CSS/JavaScript", 
        "technologies": [
            "AngularJS", 
            "CSS", 
            "Data Structures", 
            "HTML", 
            "JavaScript", 
            ".NET", 
            "SQL", 
            "Java", 
            "jQuery", 
            "MySQL", 
            "Front End", 
            "Git", 
            "C#", 
            "ASP.NET"
        ], 
        "top_source": [
            "CourseReport"
        ], 
        "tracking_groups": [
            "Java/.NET", 
            "Java/.NET", 
            "Current Market", 
            "Cleveland"
        ], 
        "tracks": "Full-Stack Web Development", 
        "twitter": {
            "followers": 633, 
            "handle": "@softwareguild", 
            "tweets": 725
        }, 
        "visas": "No", 
        "website": "http://www.thesoftwareguild.com"
    }, 
    "Tech Elevator": {
        "accreditation": "Tech Elevator is licensed under the Ohio State Board of Career Colleges and Schools. ", 
        "average_salary": "N/A", 
        "class_ratio": "1:12 - 1:15 with dedicated teaching assistants ", 
        "courses": {
            ".Net Bootcamp - Fall '16 Cleveland": {
                "Cost": 12000, 
                "Hours/Week": 60, 
                "Length": 14, 
                "Location": [
                    "Cleveland"
                ], 
                "Start Date": "Rolling Dates", 
                "Subjects": [
                    "C#", 
                    "CSS", 
                    "HTML", 
                    "Javascript", 
                    ".NET", 
                    "SQL"
                ], 
                "Title": ".NET Bootcamp - Fall '16 Cleveland"
            }, 
            ".Net Bootcamp - Spring '17 Cleveland": {
                "Cost": 12000, 
                "Hours/Week": 60, 
                "Length": 14, 
                "Location": [
                    "Akron", 
                    "Cleveland"
                ], 
                "Start Date": "2017-01-09", 
                "Subjects": [
                    "C#", 
                    "CSS", 
                    "HTML", 
                    "Javascript", 
                    ".NET", 
                    "SQL"
                ], 
                "Title": ".NET Bootcamp - Spring '17 Cleveland"
            }, 
            ".Net Coding Bootcamp": {
                "Cost": null, 
                "Hours/Week": 40, 
                "Location": [
                    "Columbus"
                ], 
                "Minimum Skill": null, 
                "Onsite": "In Person", 
                "Part Or Full": "Full Time", 
                "Subjects": [
                    "JavaScript", 
                    ".NET", 
                    "HTML", 
                    "C#", 
                    "SQL", 
                    "jQuery", 
                    "CSS"
                ], 
                "Title": ".NET Coding Bootcamp"
            }, 
            "Java Bootcamp - Fall '16 Cleveland": {
                "Cost": 12000, 
                "Hours/Week": 60, 
                "Length": 14, 
                "Location": [
                    "Cleveland"
                ], 
                "Start Date": "Rolling Dates", 
                "Subjects": [
                    "CSS", 
                    "HTML", 
                    "Java", 
                    "Javascript", 
                    "SQL"
                ], 
                "Title": "Java Bootcamp - Fall '16 Cleveland"
            }, 
            "Java Bootcamp - Spring '17 Cleveland": {
                "Cost": 12000, 
                "Hours/Week": 60, 
                "Length": 14, 
                "Location": [
                    "Cleveland"
                ], 
                "Start Date": "2017-01-09", 
                "Subjects": [
                    "CSS", 
                    "HTML", 
                    "Java", 
                    "Javascript", 
                    "SQL"
                ], 
                "Title": "Java Bootcamp - Spring '17 Cleveland"
            }, 
            "Java Coding Bootcamp": {
                "Cost": null, 
                "Hours/Week": 40, 
                "Location": [
                    "Columbus"
                ], 
                "Minimum Skill": null, 
                "Onsite": "In Person", 
                "Part Or Full": "Full Time", 
                "Subjects": [
                    "MySQL", 
                    "JavaScript", 
                    "HTML", 
                    "Java", 
                    "SQL", 
                    "jQuery", 
                    "CSS"
                ], 
                "Title": "Java Coding Bootcamp"
            }, 
            "Java/.Net Bootcamp - Fall '16 Columbus": {
                "Cost": 12000, 
                "Hours/Week": 60, 
                "Length": 14, 
                "Location": [
                    "Akron", 
                    "Columbus"
                ], 
                "Start Date": "2016-09-12", 
                "Subjects": [
                    "CSS", 
                    "HTML", 
                    "Java", 
                    "Javascript", 
                    ".NET", 
                    "SQL"
                ], 
                "Title": "Java/.NET Bootcamp - Fall '16 Columbus"
            }, 
            "Java/.Net Bootcamp - Spring '17 Columbus": {
                "Cost": 12000, 
                "Hours/Week": 60, 
                "Length": 14, 
                "Location": [
                    "Cleveland", 
                    "Columbus"
                ], 
                "Start Date": "2017-01-16", 
                "Subjects": [
                    "C#", 
                    "CSS", 
                    "HTML", 
                    "Java", 
                    "Javascript", 
                    ".NET", 
                    "SQL"
                ], 
                "Title": "Java/.NET Bootcamp - Spring '17 Columbus"
            }
        }, 
        "cr_num_reviews": 15, 
        "cr_rating": 5.0, 
        "cr_technologies": [
            "JavaScript", 
            ".NET", 
            "HTML", 
            "C#", 
            "SQL", 
            "jQuery", 
            "CSS", 
            "Java", 
            "MySQL"
        ], 
        "email": "hello@techelevator.com", 
        "facebook": "https://www.facebook.com/techelevator/", 
        "general_cost": "$$$", 
        "hiring_rate": "No data", 
        "housing": "Yes. Housing and program bundling options available in Cleveland location. Fully furnished apartments nearby classes.", 
        "job_assistance": "Yes", 
        "job_guarantee": "No", 
        "last_updated": "2016-09-09", 
        "locations": [
            "Cleveland", 
            "Columbus"
        ], 
        "name": "Tech Elevator", 
        "num_alumni": "N/A", 
        "num_courses": 2, 
        "num_locations": 2, 
        "su_num_reviews": 13, 
        "su_rating": 5.0, 
        "su_technologies": [
            "C#", 
            "CSS", 
            "HTML", 
            "JavaScript", 
            ".NET", 
            "SQL", 
            "Java"
        ], 
        "subjects": "Full Stack Web Development - Java or .NET, C#, CSS, HTML, Javascript, SQL, VB", 
        "technologies": [
            "C#", 
            "CSS", 
            "HTML", 
            "JavaScript", 
            ".NET", 
            "SQL", 
            "Java", 
            "jQuery", 
            "MySQL"
        ], 
        "top_source": [
            "CourseReport"
        ], 
        "tracking_groups": [
            "Current Market", 
            "Cleveland", 
            "Columbus"
        ], 
        "tracks": "Full-Stack Web Development", 
        "twitter": {
            "followers": 476, 
            "handle": "@Tech_Elevator", 
            "tweets": 1195
        }, 
        "visas": "No", 
        "website": "http://www.techelevator.com/"
    }, 
    "The Software Guild": {
        "average_salary": 55000, 
        "class_ratio": "1 to 12", 
        "courses": {
            ".Net Web Developer Bootcamp": {
                "Class Size": 16, 
                "Cost": 10000, 
                "Hours/Week": 60, 
                "Length": 12, 
                "Location": [
                    "Akron"
                ], 
                "Start Date": "Rolling Dates", 
                "Subjects": [
                    "AngularJS", 
                    "CSS", 
                    "Data Structures", 
                    "HTML", 
                    "Javascript", 
                    ".NET", 
                    "SQL"
                ], 
                "Title": ".NET Web Developer Bootcamp"
            }, 
            "Java Web Developer Bootcamp": {
                "Class Size": 16, 
                "Hours/Week": 60, 
                "Length": 12, 
                "Start Date": "Rolling Dates", 
                "Subjects": [
                    "CSS", 
                    "Data Structures", 
                    "HTML", 
                    "Java", 
                    "Javascript", 
                    "jQuery", 
                    "MySQL"
                ], 
                "Title": "Java Web Developer Bootcamp"
            }
        }, 
        "general_cost": "$$", 
        "hiring_rate": 95.0, 
        "last_updated": "2016-09-08", 
        "locations": [
            "Akron", 
            "Louisville", 
            "Minneapolis", 
            "Cleveland", 
            "Online"
        ], 
        "name": "The Software Guild", 
        "num_alumni": "N/A", 
        "num_locations": 5, 
        "su_num_reviews": 24, 
        "su_rating": 4.8, 
        "su_technologies": [
            "CSS", 
            "Data Structures", 
            "HTML", 
            "Java", 
            "JavaScript", 
            "jQuery", 
            "MySQL", 
            "AngularJS", 
            ".NET", 
            "SQL"
        ], 
        "subjects": "Full Stack Web Development - Java or .NET, SQL Server / MySQL, HTML/CSS/JavaScript", 
        "technologies": [
            "CSS", 
            "Data Structures", 
            "HTML", 
            "Java", 
            "JavaScript", 
            "jQuery", 
            "MySQL", 
            "AngularJS", 
            ".NET", 
            "SQL"
        ], 
        "top_source": [
            "SwitchUp"
        ], 
        "tracking_groups": [
            "Current Market", 
            "Cleveland"
        ], 
        "website": "http://www.swcguild.com"
    }, 
    "We Can Code It": {
        "accreditation": "We Can Code IT is Registered by the Ohio State Board of Career Colleges and Schools. Registration No. 15-03-2064T", 
        "average_salary": "N/A", 
        "class_ratio": null, 
        "courses": {
            "Coding Bootcamp": {
                "Cost": 10000, 
                "Hours/Week": 40, 
                "Length": 12, 
                "Location": [
                    "Cleveland"
                ], 
                "Start Date": "Rolling Dates", 
                "Subjects": [
                    "C++", 
                    "CSS", 
                    "HTML", 
                    "Javascript", 
                    ".NET"
                ], 
                "Title": "Coding Bootcamp"
            }, 
            "Full-Time Coding Bootcamp": {
                "Cost": null, 
                "Hours/Week": null, 
                "Location": [
                    "Cleveland"
                ], 
                "Minimum Skill": null, 
                "Onsite": null, 
                "Part Or Full": null, 
                "Subjects": [
                    "AngularJS", 
                    "JavaScript", 
                    ".NET", 
                    "HTML", 
                    "C#", 
                    "jQuery", 
                    "CSS"
                ], 
                "Title": "Full-Time Coding Bootcamp"
            }, 
            "Part-Time Coding Bootcamp": {
                "Cost": null, 
                "Hours/Week": null, 
                "Location": [
                    "Cleveland"
                ], 
                "Minimum Skill": null, 
                "Onsite": null, 
                "Part Or Full": null, 
                "Subjects": [
                    "AngularJS", 
                    "JavaScript", 
                    ".NET", 
                    "HTML", 
                    "Git", 
                    "C#", 
                    "SQL", 
                    "jQuery", 
                    "Mobile", 
                    "CSS"
                ], 
                "Title": "Part-Time Coding Bootcamp"
            }, 
            "Women-Only Coding Bootcamp": {
                "Cost": 9000, 
                "Hours/Week": 40, 
                "Length": 12, 
                "Location": [
                    "Cleveland"
                ], 
                "Start Date": "Rolling Dates", 
                "Subjects": [
                    "AngularJS", 
                    "C#", 
                    "CSS", 
                    "HTML", 
                    "Javascript", 
                    ".NET"
                ], 
                "Title": "Women-Only Coding Bootcamp"
            }
        }, 
        "cr_num_reviews": 20, 
        "cr_rating": 5.0, 
        "cr_technologies": [
            "AngularJS", 
            "JavaScript", 
            ".NET", 
            "HTML", 
            "C#", 
            "jQuery", 
            "CSS", 
            "Git", 
            "SQL", 
            "Mobile"
        ], 
        "email": "hello@WeCanCodeIT.org", 
        "facebook": "https://www.facebook.com/wecancodeit", 
        "general_cost": "$$", 
        "hiring_rate": "No data", 
        "housing": null, 
        "job_assistance": "Yes", 
        "job_guarantee": "No", 
        "last_updated": "2016-09-09", 
        "locations": [
            "Cleveland"
        ], 
        "name": "We Can Code It", 
        "num_alumni": "N/A", 
        "num_courses": 2, 
        "num_locations": 1, 
        "scholarships": "You will automatically...", 
        "su_num_reviews": 4, 
        "su_rating": 4.7, 
        "su_technologies": [
            "C++", 
            "CSS", 
            "HTML", 
            "JavaScript", 
            ".NET", 
            "AngularJS", 
            "C#"
        ], 
        "subjects": "Web Development, Windows .NET development, Databases / SQL, Object oriented design and Model-View-Controller design patterns", 
        "technologies": [
            "C++", 
            "CSS", 
            "HTML", 
            "JavaScript", 
            ".NET", 
            "AngularJS", 
            "C#", 
            "jQuery", 
            "Git", 
            "SQL", 
            "Mobile"
        ], 
        "top_source": [
            "CourseReport"
        ], 
        "tracking_groups": [
            "Current Market", 
            "Cleveland", 
            "Columbus"
        ], 
        "tracks": "Full-Stack Web Development", 
        "twitter": {
            "followers": 1514, 
            "handle": "@WeCanCodeIT", 
            "tweets": 1549
        }, 
        "visas": "No", 
        "website": "http://bootcamp.wecancodeit.org/"
    }
}